nimrod_reader/__init__.py
nimrod_reader/nimrod_data_defs.py
nimrod_reader/nimrod_funcs.py
nimrod_reader/read_nimrod.py
nimrod_reader_aricooperdavis-0.0.6.dist-info/LICENSE
nimrod_reader_aricooperdavis-0.0.6.dist-info/METADATA
nimrod_reader_aricooperdavis-0.0.6.dist-info/WHEEL
nimrod_reader_aricooperdavis-0.0.6.dist-info/top_level.txt
nimrod_reader_aricooperdavis-0.0.6.dist-info/RECORD
