Metadata-Version: 2.1
Name: nimrod-reader-aricooperdavis
Version: 0.0.6
Summary: Read Met Office composite radar scenes in NIMROD format
Home-page: https://github.com/aricooperdavis/NIMROD_Reader
Author: Ari Cooper-Davis
Author-email: pypi@cooper-davis.net
License: UNKNOWN
Project-URL: Bug Tracker, https://github.com/aricooperdavis/nimrod-reader/issues
Platform: UNKNOWN
Classifier: Programming Language :: Python :: 3
Classifier: License :: OSI Approved :: GNU General Public License v3 (GPLv3)
Classifier: Operating System :: OS Independent
Requires-Python: >=3
License-File: LICENSE
Requires-Dist: numpy
Requires-Dist: gdal
